mkdocs_excalidraw/__init__.py
mkdocs_excalidraw/__main__.py
mkdocs_excalidraw/assets/excalidraw-renderer.bundle.js
mkdocs_excalidraw/plugin.py
mkdocs_excalidraw-0.6.0.dist-info/METADATA
mkdocs_excalidraw-0.6.0.dist-info/WHEEL
mkdocs_excalidraw-0.6.0.dist-info/entry_points.txt
mkdocs_excalidraw-0.6.0.dist-info/licenses/LICENSE
mkdocs_excalidraw-0.6.0.dist-info/RECORD
