Metadata-Version: 2.4
Name: mkdocs-excalidraw
Version: 0.6.0
Summary: Excalidraw drawings in mkdocs
License-File: LICENSE
Author: qdeli
Requires-Python: >=3.10
Classifier: Programming Language :: Python :: 3
Classifier: Operating System :: OS Independent
Requires-Dist: beautifulsoup4 (>=4.13.5,<5.0.0)
Requires-Dist: mkdocs (>=1.6.1,<2.0.0)
Project-URL: Changelog, https://github.com/qdeli187/mkdocs-excalidraw/releases
Project-URL: Documentation, https://qdeli187.github.io/mkdocs-excalidraw/
Project-URL: Homepage, https://github.com/qdeli187/mkdocs-excalidraw
Project-URL: Issues, https://github.com/qdeli187/mkdocs-excalidraw/issues
Project-URL: Repository, https://github.com/qdeli187/mkdocs-excalidraw
